redmab/VERSION
redmab/__init__.py
redmab/luascripts.py
redmab/thompson.py
redmab/version.py
redmab-0.0.5.dist-info/METADATA
redmab-0.0.5.dist-info/WHEEL
redmab-0.0.5.dist-info/top_level.txt
redmab-0.0.5.dist-info/RECORD
