Metadata-Version: 2.1
Name: redmab
Version: 0.0.5
Summary: Multi-Armed Bandit implementation in redis
Home-page: https://github.com/72squared/redmab
Author: John Loehrer
Author-email: 72squared@gmail.com
License: MIT
Download-URL: https://github.com/72squared/redmab/archive/0.0.5.tar.gz
Keywords: redis multi-armed bandit
Platform: UNKNOWN
Classifier: Development Status :: 3 - Alpha
Classifier: Programming Language :: Python
Classifier: Programming Language :: Python :: 2
Classifier: Programming Language :: Python :: 3
Classifier: Environment :: Web Environment
Classifier: Operating System :: POSIX
Requires-Dist: redpipe (>=2.0.0)
